chuk_mcp_pptx/__init__.py
chuk_mcp_pptx/async_server.py
chuk_mcp_pptx/constants.py
chuk_mcp_pptx/server.py
chuk_mcp_pptx/components/__init__.py
chuk_mcp_pptx/components/base.py
chuk_mcp_pptx/components/code.py
chuk_mcp_pptx/components/composition.py
chuk_mcp_pptx/components/registry.py
chuk_mcp_pptx/components/tracking.py
chuk_mcp_pptx/components/variants.py
chuk_mcp_pptx/components/charts/__init__.py
chuk_mcp_pptx/components/charts/base.py
chuk_mcp_pptx/components/charts/column_bar.py
chuk_mcp_pptx/components/charts/funnel.py
chuk_mcp_pptx/components/charts/line_area.py
chuk_mcp_pptx/components/charts/pie_doughnut.py
chuk_mcp_pptx/components/charts/radar_combo.py
chuk_mcp_pptx/components/charts/scatter_bubble.py
chuk_mcp_pptx/components/chat/__init__.py
chuk_mcp_pptx/components/chat/android.py
chuk_mcp_pptx/components/chat/aol.py
chuk_mcp_pptx/components/chat/chatgpt.py
chuk_mcp_pptx/components/chat/facebook.py
chuk_mcp_pptx/components/chat/generic.py
chuk_mcp_pptx/components/chat/ios.py
chuk_mcp_pptx/components/chat/msn.py
chuk_mcp_pptx/components/chat/slack.py
chuk_mcp_pptx/components/chat/teams.py
chuk_mcp_pptx/components/chat/whatsapp.py
chuk_mcp_pptx/components/containers/__init__.py
chuk_mcp_pptx/components/containers/browser.py
chuk_mcp_pptx/components/containers/generic.py
chuk_mcp_pptx/components/containers/iphone.py
chuk_mcp_pptx/components/containers/macos.py
chuk_mcp_pptx/components/containers/samsung.py
chuk_mcp_pptx/components/containers/windows.py
chuk_mcp_pptx/components/core/__init__.py
chuk_mcp_pptx/components/core/alert.py
chuk_mcp_pptx/components/core/avatar.py
chuk_mcp_pptx/components/core/badge.py
chuk_mcp_pptx/components/core/button.py
chuk_mcp_pptx/components/core/card.py
chuk_mcp_pptx/components/core/connector.py
chuk_mcp_pptx/components/core/container.py
chuk_mcp_pptx/components/core/content_grid.py
chuk_mcp_pptx/components/core/divider.py
chuk_mcp_pptx/components/core/grid.py
chuk_mcp_pptx/components/core/icon.py
chuk_mcp_pptx-0.4.dist-info/METADATA
chuk_mcp_pptx-0.4.dist-info/WHEEL
chuk_mcp_pptx-0.4.dist-info/entry_points.txt
chuk_mcp_pptx-0.4.dist-info/RECORD
