Metadata-Version: 2.4
Name: chuk-mcp-pptx
Version: 0.4
Summary: PowerPoint MCP Server - A shadcn-inspired design system for presentations
Author: Chris Hay
Requires-Python: >=3.11
Requires-Dist: aiobotocore>=2.5.0
Requires-Dist: aiofiles>=23.0.0
Requires-Dist: chuk-artifacts
Requires-Dist: chuk-mcp-server>=0.15.1
Requires-Dist: mcp>=0.9.1
Requires-Dist: pillow>=10.0.0
Requires-Dist: python-dotenv>=1.1.1
Requires-Dist: python-pptx>=1.0.2
Requires-Dist: redis>=5.0.0
Provides-Extra: dev
Requires-Dist: bandit>=1.7.0; extra == 'dev'
Requires-Dist: black>=23.0.0; extra == 'dev'
Requires-Dist: flake8>=6.0.0; extra == 'dev'
Requires-Dist: isort>=5.12.0; extra == 'dev'
Requires-Dist: mypy>=1.0.0; extra == 'dev'
Requires-Dist: pylint>=2.17.0; extra == 'dev'
Requires-Dist: pytest-asyncio>=0.21.0; extra == 'dev'
Requires-Dist: pytest-cov>=4.0.0; extra == 'dev'
Requires-Dist: pytest-mock>=3.10.0; extra == 'dev'
Requires-Dist: pytest>=7.0.0; extra == 'dev'
Requires-Dist: ruff>=0.1.0; extra == 'dev'
Requires-Dist: twine>=4.0.0; extra == 'dev'
